pypicloud/__init__.py
pypicloud/_lambda_handler.py
pypicloud/auth.py
pypicloud/dateutil.py
pypicloud/lambda_scripts.py
pypicloud/locator.py
pypicloud/models.py
pypicloud/route.py
pypicloud/scripts.py
pypicloud/util.py
pypicloud/access/__init__.py
pypicloud/access/aws_secrets_manager.py
pypicloud/access/base.py
pypicloud/access/base_json.py
pypicloud/access/config.py
pypicloud/access/ldap_.py
pypicloud/access/remote.py
pypicloud/access/sql.py
pypicloud/cache/__init__.py
pypicloud/cache/base.py
pypicloud/cache/dynamo.py
pypicloud/cache/redis_cache.py
pypicloud/cache/sql.py
pypicloud/static/css/base.css
pypicloud/static/css/lib/bootstrap-3.0.3.min.css
pypicloud/static/css/lib/font-awesome-4.0.3/css/font-awesome.min.css
pypicloud/static/css/lib/font-awesome-4.0.3/fonts/FontAwesome.otf
pypicloud/static/css/lib/font-awesome-4.0.3/fonts/fontawesome-webfont.eot
pypicloud/static/css/lib/font-awesome-4.0.3/fonts/fontawesome-webfont.svg
pypicloud/static/css/lib/font-awesome-4.0.3/fonts/fontawesome-webfont.ttf
pypicloud/static/css/lib/font-awesome-4.0.3/fonts/fontawesome-webfont.woff
pypicloud/static/js/admin.js
pypicloud/static/js/pypicloud.js
pypicloud/static/js/lib/angular-file-upload.min.js
pypicloud/static/js/lib/angular-file-upload.min.map
pypicloud/static/js/lib/ui-bootstrap-tpls-0.10.0.min.js
pypicloud/static/js/lib/angularjs/1.2.14/angular-cookies.min.js
pypicloud/static/js/lib/angularjs/1.2.14/angular-cookies.min.js.map
pypicloud/static/js/lib/angularjs/1.2.14/angular-route.min.js
pypicloud/static/js/lib/angularjs/1.2.14/angular-route.min.js.map
pypicloud/static/js/lib/angularjs/1.2.14/angular-sanitize.min.js
pypicloud/static/js/lib/angularjs/1.2.14/angular.min.js
pypicloud/static/js/lib/angularjs/1.2.14/angular.min.js.map
pypicloud/static/js/lib/underscore/1.13.1/underscore-umd-min.js
pypicloud/static/partial/account.html
pypicloud/static/partial/index.html
pypicloud/static/partial/login.html
pypicloud/static/partial/navbar.html
pypicloud-1.3.12.dist-info/LICENSE
pypicloud-1.3.12.dist-info/METADATA
pypicloud-1.3.12.dist-info/WHEEL
pypicloud-1.3.12.dist-info/entry_points.txt
pypicloud-1.3.12.dist-info/top_level.txt
pypicloud-1.3.12.dist-info/RECORD
