Metadata-Version: 2.1
Name: pypicloud
Version: 1.3.12
Summary: Private PyPI backed by S3
Home-page: http://pypicloud.readthedocs.org/
Author: Steven Arcangeli
Author-email: stevearc@stevearc.com
License: MIT
Keywords: pypi s3 cheeseshop package
Platform: any
Classifier: Programming Language :: Python
Classifier: Programming Language :: Python :: 3
Classifier: Programming Language :: Python :: 3.7
Classifier: Programming Language :: Python :: 3.8
Classifier: Programming Language :: Python :: 3.9
Classifier: Development Status :: 4 - Beta
Classifier: Framework :: Pyramid
Classifier: Intended Audience :: System Administrators
Classifier: Intended Audience :: Developers
Classifier: License :: OSI Approved :: MIT License
Classifier: Topic :: Internet :: WWW/HTTP
Classifier: Topic :: System :: Systems Administration
Requires-Python: >=3.7
License-File: LICENSE
Requires-Dist: boto3 (>=1.7.0)
Requires-Dist: cryptography
Requires-Dist: distlib
Requires-Dist: passlib (>=1.7)
Requires-Dist: paste
Requires-Dist: pyramid (>=2)
Requires-Dist: pyramid-beaker
Requires-Dist: pyramid-duh
Requires-Dist: pyramid-jinja2
Requires-Dist: pyramid-rpc
Requires-Dist: pyramid-tm
Requires-Dist: requests
Requires-Dist: smart-open[http,s3]
Requires-Dist: transaction
Requires-Dist: zope.sqlalchemy
Provides-Extra: all_plugins
Requires-Dist: azure-storage-blob (>=12.5.0) ; extra == 'all_plugins'
Requires-Dist: flywheel (>=0.2.0) ; extra == 'all_plugins'
Requires-Dist: google-cloud-storage (>=1.10.0) ; extra == 'all_plugins'
Requires-Dist: python-ldap ; extra == 'all_plugins'
Requires-Dist: redis ; extra == 'all_plugins'
Requires-Dist: smart-open[azure] (>=6.1.0) ; extra == 'all_plugins'
Requires-Dist: smart-open[gcs] (>=6.3.0) ; extra == 'all_plugins'
Provides-Extra: azure-blob
Requires-Dist: azure-storage-blob (>=12.5.0) ; extra == 'azure-blob'
Requires-Dist: smart-open[azure] (>=6.1.0) ; extra == 'azure-blob'
Provides-Extra: dynamo
Requires-Dist: flywheel (>=0.2.0) ; extra == 'dynamo'
Provides-Extra: gcs
Requires-Dist: google-cloud-storage (>=1.10.0) ; extra == 'gcs'
Requires-Dist: smart-open[gcs] (>=6.3.0) ; extra == 'gcs'
Provides-Extra: ldap
Requires-Dist: python-ldap ; extra == 'ldap'
Provides-Extra: redis
Requires-Dist: redis ; extra == 'redis'
Provides-Extra: server
Requires-Dist: waitress ; extra == 'server'
